bitaddress/base58.py
bitaddress/__init__.py
bitaddress-0.1.dist-info/DESCRIPTION.rst
bitaddress-0.1.dist-info/METADATA
bitaddress-0.1.dist-info/metadata.json
bitaddress-0.1.dist-info/RECORD
bitaddress-0.1.dist-info/top_level.txt
bitaddress-0.1.dist-info/WHEEL
