Metadata-Version: 2.0
Name: bitaddress
Version: 0.1
Summary: Generate bitcoin addresses
Home-page: https://github.com/pta2002/bitaddress
Author: Pedro Alves
Author-email: pta2002@pta2002.com
License: MIT
Platform: UNKNOWN
Requires-Dist: ecdsa
